{
  "$schema": "https://json-schema.org/draft/2020-12/schema",
  "$id": "https://jarvis.ai/schemas/telemetry-events.schema.json",
  "title": "TelemetryEvent",
  "type": "object",
  "additionalProperties": false,
  "required": [
    "id",
    "workspace_id",
    "category",
    "severity",
    "event_type",
    "message",
    "created_at",
    "updated_at"
  ],
  "properties": {
    "id": { "type": "string", "format": "uuid" },
    "workspace_id": { "type": "string", "format": "uuid" },
    "agent_id": { "type": "string", "format": "uuid" },
    "task_id": { "type": "string", "format": "uuid" },
    "project_id": { "type": "string", "format": "uuid" },
    "category": {
      "type": "string",
      "enum": ["heartbeat", "log", "metric", "event", "error"]
    },
    "severity": {
      "type": "string",
      "enum": ["info", "warning", "critical"]
    },
    "event_type": { "type": "string" },
    "message": { "type": "string" },
    "payload": { "type": "object", "additionalProperties": true },
    "latency_ms": { "type": "number", "minimum": 0 },
    "tokens_input": { "type": "integer", "minimum": 0 },
    "tokens_output": { "type": "integer", "minimum": 0 },
    "cost_usd": { "type": "number", "minimum": 0 },
    "correlation_id": { "type": "string" },
    "created_at": { "type": "string", "format": "date-time" },
    "updated_at": { "type": "string", "format": "date-time" }
  }
}
